yoolkit/__init__.py
yoolkit/arguments.py
yoolkit/cio.py
yoolkit/constant.py
yoolkit/decorator.py
yoolkit/gio.py
yoolkit/levenshtein.py
yoolkit/logging.py
yoolkit/multiprocessing.py
yoolkit/registration.py
yoolkit/statistics.py
yoolkit/text.py
yoolkit/timer.py
yoolkit/tracker.py
yoolkit/visualizing.py
yoolkit/xmlscape.py
YoungToolkit-0.1.3.1.dist-info/LICENSE
YoungToolkit-0.1.3.1.dist-info/METADATA
YoungToolkit-0.1.3.1.dist-info/WHEEL
YoungToolkit-0.1.3.1.dist-info/top_level.txt
YoungToolkit-0.1.3.1.dist-info/RECORD
