Metadata-Version: 2.1
Name: YoungToolkit
Version: 0.1.3.1
Summary: A Toolkit for a series of Young projects
Home-page: https://github.com/Jason-Young-AI/YoungToolkit
Author: Jason-Young-AI
Author-email: AI.Jason.Young@gmail.com
License: UNKNOWN
Platform: UNKNOWN
Classifier: Intended Audience :: Science/Research
Classifier: Programming Language :: Python :: 3
Classifier: License :: OSI Approved :: Apache Software License
Classifier: Operating System :: OS Independent
Classifier: Topic :: Scientific/Engineering :: Artificial Intelligence
Requires-Dist: visdom
Requires-Dist: pyhocon
Provides-Extra: full
Requires-Dist: numpy ; extra == 'full'
Requires-Dist: torch ; extra == 'full'
Requires-Dist: pynvml ; extra == 'full'
Provides-Extra: nv-io
Requires-Dist: torch ; extra == 'nv-io'
Provides-Extra: nv-track
Requires-Dist: numpy ; extra == 'nv-track'
Requires-Dist: torch ; extra == 'nv-track'
Requires-Dist: pynvml ; extra == 'nv-track'
